pytoppa/__init__.py
pytoppa/app.py
pytoppa/utils.py
pytoppa/contexts/__init__.py
pytoppa/contexts/base.py
pytoppa/contexts/globals.py
pytoppa/contexts/release.py
pytoppa/helpers/__init__.py
pytoppa/helpers/base.py
pytoppa/helpers/import_scope.py
pytoppa/helpers/package_data.py
pytoppa/helpers/revision.py
pytoppa/helpers/temporary.py
pytoppa/parsers/__init__.py
pytoppa/parsers/config_parser.py
pytoppa/parsers/exceptions.py
pytoppa/parsers/git_parser.py
pytoppa/parsers/setup_parser.py
pytoppa/templates/__init__.py
pytoppa/templates/changelog.tmpl
pytoppa/templates/clean.tmpl
pytoppa/templates/compat.tmpl
pytoppa/templates/control.tmpl
pytoppa/templates/copyright.tmpl
pytoppa/templates/docs.tmpl
pytoppa/templates/revision_setup_py.tmpl
pytoppa/templates/rules.tmpl
pytoppa/templates/setup.py.tmpl
pytoppa/templates/source/__init__.py
pytoppa/templates/source/format.tmpl
pytoppa-15.0.2.dist-info/DESCRIPTION.rst
pytoppa-15.0.2.dist-info/METADATA
pytoppa-15.0.2.dist-info/RECORD
pytoppa-15.0.2.dist-info/WHEEL
pytoppa-15.0.2.dist-info/entry_points.txt
pytoppa-15.0.2.dist-info/metadata.json
pytoppa-15.0.2.dist-info/top_level.txt
