Metadata-Version: 2.0
Name: pytoppa
Version: 15.0.2
Summary: Easy to use publisher of python packages to ppa
Home-page: https://github.com/nvbn/pytoppa
Author: Vladimir Iakovlev
Author-email: nvbn.rm@gmail.com
License: MIT
Platform: UNKNOWN
Requires-Dist: Jinja2
Requires-Dist: PyYAML
